anndata/__init__.py
anndata/_version.py
anndata/base.py
anndata/logging.py
anndata/utils.py
anndata/h5py/__init__.py
anndata/h5py/h5sparse.py
anndata/readwrite/__init__.py
anndata/readwrite/read.py
anndata/readwrite/utils.py
anndata/readwrite/write.py
anndata_modified-0.6.4.post2.dist-info/LICENSE
anndata_modified-0.6.4.post2.dist-info/METADATA
anndata_modified-0.6.4.post2.dist-info/WHEEL
anndata_modified-0.6.4.post2.dist-info/top_level.txt
anndata_modified-0.6.4.post2.dist-info/RECORD
