Metadata-Version: 2.1
Name: anndata-modified
Version: 0.6.4.post2
Summary: Forked package from anndata v0.6.4, with a bug fix on reading string features. This fix was done following anndata official repository, but was not added to v0.6.4.
Home-page: https://github.com/lilab-bcb/anndata
Author: Alex Wolf, Philipp Angerer
Author-email: alex.wolf@helmholtz-muenchen.de
License: BSD-3-Clause
Platform: UNKNOWN
Classifier: Environment :: Console
Classifier: Framework :: Jupyter
Classifier: Intended Audience :: Developers
Classifier: Intended Audience :: Science/Research
Classifier: Natural Language :: English
Classifier: Operating System :: MacOS :: MacOS X
Classifier: Operating System :: Microsoft :: Windows
Classifier: Operating System :: POSIX :: Linux
Classifier: Programming Language :: Python :: 3
Classifier: Programming Language :: Python :: 3.5
Classifier: Programming Language :: Python :: 3.6
Classifier: Topic :: Scientific/Engineering :: Bio-Informatics
Classifier: Topic :: Scientific/Engineering :: Visualization
Requires-Dist: pandas (>=0.21.0)
Requires-Dist: scipy
Requires-Dist: h5py
Requires-Dist: natsort
